[
  {
    "id": 1650021425530,
    "value": "valueTest",
    "isCorrect": false,
    "questionId": 1650021425527
  },
  {
    "id": 1650022481973,
    "value": "Vraie",
    "isCorrect": true,
    "questionId": 1650022481970
  },
  {
    "id": 1650022481975,
    "value": "Fausse",
    "isCorrect": false,
    "questionId": 1650022481970
  },
  {
    "id": 1650022481977,
    "value": "Fausse 2",
    "isCorrect": false,
    "questionId": 1650022481970
  },
  {
    "id": 1650022481978,
    "value": "valueTest",
    "isCorrect": false,
    "questionId": 1650022481970
  },
  {
    "id": 1650022493933,
    "value": "Vraie",
    "isCorrect": true,
    "questionId": 1650022493931
  },
  {
    "id": 1650022493934,
    "value": "Fausse",
    "isCorrect": false,
    "questionId": 1650022493931
  },
  {
    "id": 1650022493935,
    "value": "Fausse 2",
    "isCorrect": false,
    "questionId": 1650022493931
  },
  {
    "id": 1650022493936,
    "value": "valueTest",
    "isCorrect": false,
    "questionId": 1650022493931
  },
  {
    "id": 1650022493937,
    "value": "valueTest",
    "isCorrect": false,
    "questionId": 1650022493931
  },
  {
    "id": 1650022496680,
    "value": "Vraie",
    "isCorrect": true,
    "questionId": 1650022496679
  },
  {
    "id": 1650022496681,
    "value": "Fausse",
    "isCorrect": false,
    "questionId": 1650022496679
  },
  {
    "id": 1650022496682,
    "value": "Fausse 2",
    "isCorrect": false,
    "questionId": 1650022496679
  },
  {
    "id": 1650022496683,
    "value": "valueTest",
    "isCorrect": false,
    "questionId": 1650022496679
  },
  {
    "id": 1650022496685,
    "value": "valueTest",
    "isCorrect": false,
    "questionId": 1650022496679
  },
  {
    "id": 1650022500113,
    "value": "Vraie",
    "isCorrect": true,
    "questionId": 1650022500112
  },
  {
    "id": 1650022500114,
    "value": "Fausse",
    "isCorrect": false,
    "questionId": 1650022500112
  },
  {
    "id": 1650022500115,
    "value": "Fausse 2",
    "isCorrect": false,
    "questionId": 1650022500112
  },
  {
    "id": 1650022500116,
    "value": "valueTest",
    "isCorrect": false,
    "questionId": 1650022500112
  },
  {
    "id": 1650022500117,
    "value": "valueTest",
    "isCorrect": false,
    "questionId": 1650022500112
  },
  {
    "id": 1650022503940,
    "value": "Vraie",
    "isCorrect": true,
    "questionId": 1650022503939
  },
  {
    "id": 1650022503941,
    "value": "Fausse",
    "isCorrect": false,
    "questionId": 1650022503939
  },
  {
    "id": 1650022503942,
    "value": "Fausse 2",
    "isCorrect": false,
    "questionId": 1650022503939
  },
  {
    "id": 1650022503944,
    "value": "valueTest",
    "isCorrect": false,
    "questionId": 1650022503939
  },
  {
    "id": 1650022503945,
    "value": "valueTest",
    "isCorrect": false,
    "questionId": 1650022503939
  },
  {
    "id": 1650022503946,
    "value": "valueTest",
    "isCorrect": false,
    "questionId": 1650022503939
  },
  {
    "id": 1650042254907,
    "value": "valueTest",
    "isCorrect": false,
    "questionId": 1650042254907
  },
  {
    "id": 1650042254908,
    "value": "valueTest",
    "isCorrect": false,
    "questionId": 1650042254907
  },
  {
    "id": 1650042254909,
    "value": "valueTest",
    "isCorrect": false,
    "questionId": 1650042254907
  },
  {
    "id": 1650314346555,
    "value": "valueTest",
    "isCorrect": true,
    "questionId": 1650314346543
  },
  {
    "id": 1650314605328,
    "value": "valueTest",
    "isCorrect": true,
    "questionId": 1650314605323
  },
  {
    "id": 1650314605331,
    "value": "valueTest",
    "isCorrect": false,
    "questionId": 1650314605323
  },
  {
    "id": 1650314607886,
    "value": "valueTest",
    "isCorrect": true,
    "questionId": 1650314607883
  },
  {
    "id": 1650314607889,
    "value": "valueTest",
    "isCorrect": false,
    "questionId": 1650314607883
  },
  {
    "id": 1650314609034,
    "value": "valueTest",
    "isCorrect": true,
    "questionId": 1650314609030
  },
  {
    "id": 1650314609037,
    "value": "valueTest",
    "isCorrect": false,
    "questionId": 1650314609030
  },
  {
    "id": 1650314680305,
    "value": "valueTest",
    "isCorrect": false,
    "questionId": 1650314680302
  },
  {
    "id": 1650314681112,
    "value": "valueTest",
    "isCorrect": false,
    "questionId": 1650314681109
  },
  {
    "id": 1650537254186,
    "value": "aaaaaaaaa",
    "isCorrect": true,
    "questionId": 1650537254179
  },
  {
    "id": 1650537254187,
    "value": "bbbb",
    "isCorrect": false,
    "questionId": 1650537254179
  },
  {
    "id": 1650537254188,
    "value": "ccccc",
    "isCorrect": false,
    "questionId": 1650537254179
  },
  {
    "id": 1650584246780,
    "value": "senegal",
    "isCorrect": false,
    "questionId": 1650584246740
  },
  {
    "id": 1650584246780,
    "value": "egypt",
    "isCorrect": false,
    "questionId": 1650584246740
  },
  {
    "id": 1650807146610,
    "value": "valueTest",
    "isCorrect": false,
    "questionId": 1650807146600
  },
  {
    "id": 1650807146611,
    "value": "valueTest",
    "isCorrect": false,
    "questionId": 1650807146600
  },
  {
    "id": 1650807146611,
    "value": "valueTest",
    "isCorrect": false,
    "questionId": 1650807146600
  },
  {
    "id": 1650807146612,
    "value": "valueTest",
    "isCorrect": true,
    "questionId": 1650807146600
  },
  {
    "id": 1650807146807,
    "value": "valueTest",
    "isCorrect": false,
    "questionId": 1650807146802
  },
  {
    "id": 1650807146808,
    "value": "valueTest",
    "isCorrect": false,
    "questionId": 1650807146802
  },
  {
    "id": 1650807146809,
    "value": "valueTest",
    "isCorrect": false,
    "questionId": 1650807146802
  },
  {
    "id": 1650807146810,
    "value": "valueTest",
    "isCorrect": true,
    "questionId": 1650807146802
  },
  {
    "id": 1650832438712,
    "value": "simba",
    "isCorrect": true,
    "questionId": 1650832438673
  },
  {
    "id": 1650832438715,
    "value": "scare",
    "isCorrect": false,
    "questionId": 1650832438673
  },
  {
    "id": 1650832438717,
    "value": "sid",
    "isCorrect": false,
    "questionId": 1650832438673
  },
  {
    "id": 1650832566314,
    "value": "ariel",
    "isCorrect": true,
    "questionId": 1650832566280
  },
  {
    "id": 1650832566317,
    "value": "adele",
    "isCorrect": false,
    "questionId": 1650832566280
  },
  {
    "id": 1650833029158,
    "value": "le bihatlon",
    "isCorrect": true,
    "questionId": 1650833029119
  },
  {
    "id": 1650833029160,
    "value": "le speed riding",
    "isCorrect": false,
    "questionId": 1650833029119
  },
  {
    "id": 1650833029164,
    "value": "Le bobsleigh",
    "isCorrect": false,
    "questionId": 1650833029119
  },
  {
    "id": 1650833029167,
    "value": "le skeleton",
    "isCorrect": false,
    "questionId": 1650833029119
  },
  {
    "id": 1650833029169,
    "value": "Le curling",
    "isCorrect": false,
    "questionId": 1650833029119
  },
  {
    "id": 1650833029172,
    "value": "Le bandy",
    "isCorrect": false,
    "questionId": 1650833029119
  },
  {
    "id": 1650954854657,
    "value": "Atlanta",
    "isCorrect": true,
    "questionId": 1650954854643
  },
  {
    "id": 1650954854661,
    "value": "Los Angeles",
    "isCorrect": false,
    "questionId": 1650954854643
  },
  {
    "id": 1650954854664,
    "value": "New York",
    "isCorrect": false,
    "questionId": 1650954854643
  },
  {
    "id": 1650954854667,
    "value": "Rio De Janeiro",
    "isCorrect": false,
    "questionId": 1650954854643
  },
  {
    "id": 1650954999522,
    "value": "Shae-Lynn Bourne et Victor Kraatz",
    "isCorrect": false,
    "questionId": 1650954999508
  },
  {
    "id": 1650954999526,
    "value": "Jamie Salé et David Pelletier",
    "isCorrect": true,
    "questionId": 1650954999508
  },
  {
    "id": 1650954999529,
    "value": "Meaghan Duhamel et Eric Radfod",
    "isCorrect": false,
    "questionId": 1650954999508
  },
  {
    "id": 1650959582322,
    "value": "Atlanta",
    "isCorrect": true,
    "questionId": 1650959582300
  },
  {
    "id": 1650959582326,
    "value": "lille",
    "isCorrect": false,
    "questionId": 1650959582300
  }
]